pico_hid/__init__.py
pico_hid/ascii_to_hid.py
pico_hid/keyboard.py
pico_hid/mouse.py
pico_hid/py.typed
pico_hid/serial_com.py
pico_hid-1.0.1.dist-info/LICENSE
pico_hid-1.0.1.dist-info/METADATA
pico_hid-1.0.1.dist-info/WHEEL
pico_hid-1.0.1.dist-info/top_level.txt
pico_hid-1.0.1.dist-info/RECORD
