Metadata-Version: 2.1
Name: pico-hid
Version: 1.0.1
Summary: Python package to control pico spoofed as keyboard/mouse via serial pins (uart)
Author-email: Pradish Bijukchhe <pradish@sandbox.com.np>
License: Copyright (c) 2018 The Python Packaging Authority
Project-URL: Homepage, https://github.com/sandbox-pokhara/pico-hid
Project-URL: Issues, https://github.com/sandbox-pokhara/pico-hid/issues
Classifier: Programming Language :: Python :: 3
Requires-Python: >=3
License-File: LICENSE
Requires-Dist: pyserial
